{
  "mainName": "Bene fotografia",
  "slug": "bene-fotografia",
  "category": "Serviço de fotografia",
  "locationInformation": {
    "latitude": "-23.6807779",
    "longitude": "-46.7406823"
  },
  "basicInformation": null,
  "ratingInformation": {
    "basicRatingInformation": {
      "averageGrade": 5,
      "totalOfEvaluations": 20
    },
    "ratingsByGrade": [
      {
        "grade": 5,
        "totalRatings": 20
      },
      {
        "grade": 4,
        "totalRatings": 0
      },
      {
        "grade": 3,
        "totalRatings": 0
      },
      {
        "grade": 2,
        "totalRatings": 0
      },
      {
        "grade": 1,
        "totalRatings": 0
      }
    ]
  },
  "ratingTags": null,
  "featuredPhotos": [
    "https://lh5.googleusercontent.com/p/AF1QipMgs8UddU8h2OhtA9aKsrDALPgutXa3sZFrE7F0=w1024-h576-k-no",
    "https://lh5.googleusercontent.com/p/AF1QipOljJl_bcwQHxcNHO_NvQIZlifZS_vlBtSHXWLh=w1024-h576-k-no",
    "https://streetviewpixels-pa.googleapis.com/v1/thumbnail?panoid=433HKga9PZ3vWHWJWBbRsQ&amp;cb_client=maps_sv.tactile.gps&amp;w=203&amp;h=100&amp;yaw=58.114063&amp;pitch=0&amp;thumbfov=100=w1024-h576-k-no",
    "https://lh5.googleusercontent.com/p/AF1QipPZvgsoCsRp4vgDNlCxQmspr8kEkstWOaVD5iZc=w1024-h576-k-no"
  ],
  "topComments": null,
  "peakHours": null,
  "relatedSearches": null,
  "relateds": null
}