{
  "mainName": "Blaster Troca de Fechaduras Miolo Segredo Aberturas Oswaldo Cruz",
  "slug": "blaster-troca-de-fechaduras-miolo-segredo-aberturas-oswaldo-cruz",
  "category": "Loja",
  "locationInformation": {
    "latitude": "-23.625899",
    "longitude": "-46.5650606"
  },
  "basicInformation": [
    {
      "label": "endereço",
      "tooltip": "Copiar endereço",
      "text": "R. Bertolino da Cunha, 287 - Osvaldo Cruz, São Caetano do Sul - SP, 09540-300",
      "icon": "https://www.gstatic.com/images/icons/material/system_gm/1x/place_gm_blue_24dp.png"
    },
    {
      "label": "Code",
      "tooltip": "Copiar Plus Code",
      "text": "9CFM+JX Osvaldo Cruz, São Caetano do Sul - SP",
      "icon": "https://maps.gstatic.com/mapfiles/maps_lite/images/2x/ic_plus_code.png"
    }
  ],
  "ratingInformation": null,
  "ratingTags": null,
  "featuredPhotos": [
    "https://streetviewpixels-pa.googleapis.com/v1/thumbnail?panoid=hyK8-tSz4WHZyf4sHkd9hg&amp;cb_client=maps_sv.tactile.gps&amp;w=203&amp;h=100&amp;yaw=17.514364&amp;pitch=0&amp;thumbfov=100=w1024-h576-k-no"
  ],
  "topComments": null,
  "peakHours": null,
  "relatedSearches": null,
  "relateds": [
    {
      "mainName": "Troca de Fechaduras Digitais",
      "url": "https://www.google.com/maps/search/Troca+de+Fechaduras+Digitais+-+Rua+Jataituba+-+Jardim+das+Acacias,+S%C3%A3o+Paulo+-+SP,+04704-090"
    },
    {
      "mainName": "Chaveiro e Afiador Oswaldo Cruz",
      "url": "https://www.google.com/maps/search/Chaveiro+e+Afiador+Oswaldo+Cruz+-+Rua+Oswaldo+Cruz,+253+-+Santa+Paula,+S%C3%A3o+Caetano+do+Sul+-+SP,+09541-270"
    },
    {
      "mainName": "Troca de Fechaduras Miolo Segredo - Vila Carioca",
      "url": "https://www.google.com/maps/search/Troca+de+Fechaduras+Miolo+Segredo+-+Vila+Carioca+-+R.+Abatixi+-+Vila+Carioca,+S%C3%A3o+Paulo+-+SP,+04225-010"
    },
    {
      "mainName": "Troca de Fechaduras Miolo Segredo VILA SANTA CLARA",
      "url": "https://www.google.com/maps/search/Troca+de+Fechaduras+Miolo+Segredo+VILA+SANTA+CLARA+-+R.+Ant%C3%B4nio+Gomes+-+Vila+Santa+Clara,+S%C3%A3o+Paulo+-+SP,+03274-010"
    },
    {
      "mainName": "Troca de Miolo Segredo Fechadura",
      "url": "https://www.google.com/maps/search/Troca+de+Miolo+Segredo+Fechadura+-+Rua+Albino+Demarchi+-+Demarchi,+S%C3%A3o+Bernardo+do+Campo+-+SP,+09820-410"
    },
    {
      "mainName": "Troca de Fechaduras Miolo Segredo - Jardim Europa",
      "url": "https://www.google.com/maps/search/Troca+de+Fechaduras+Miolo+Segredo+-+Jardim+Europa+-+Av.+Europa+-+Jardim+Europa,+S%C3%A3o+Paulo+-+SP,+01449-001"
    },
    {
      "mainName": "isabelaTroca De Fechaduras Miolo Segredo Bom Retiro",
      "url": "https://www.google.com/maps/search/isabelaTroca+De+Fechaduras+Miolo+Segredo+Bom+Retiro+-+R.+J%C3%BAlio+Concei%C3%A7%C3%A3o+-+Bom+Retiro,+S%C3%A3o+Paulo+-+SP,+01126-001"
    },
    {
      "mainName": "Edy Cofres Chaveiro",
      "url": "https://www.google.com/maps/search/Edy+Cofres+Chaveiro,+Mercado+Joanin+-+Rua+Oswaldo+Cruz,+1363+-+Santa+Paula,+S%C3%A3o+Caetano+do+Sul+-+SP,+09540-280"
    },
    {
      "mainName": "Troca de Fechaduras Miolo Segredo Aberturas Cidade Dutra",
      "url": "https://www.google.com/maps/search/Troca+de+Fechaduras+Miolo+Segredo+Aberturas+Cidade+Dutra+-+R.+Santa+Greg%C3%B3ria,+250+-+Cidade+Dutra,+S%C3%A3o+Paulo+-+SP,+04806-030"
    },
    {
      "mainName": "Chaveiro Genival",
      "url": "https://www.google.com/maps/search/Chaveiro+Genival+-+Av.+Fernando+Simonsen,+555+-+S%C3%A3o+Jos%C3%A9,+S%C3%A3o+Caetano+do+Sul+-+SP,+09540-230"
    },
    {
      "mainName": "Troca de Fechaduras Miolo Segredo Jardim Europa",
      "url": "https://www.google.com/maps/search/Troca+de+Fechaduras+Miolo+Segredo+Jardim+Europa+-+R.+Baviera+-+Jardim+Europa,+S%C3%A3o+Paulo+-+SP,+01448-060"
    },
    {
      "mainName": "Troca de Fechaduras Miolo Segredo Abertura de Carro Casa",
      "url": "https://www.google.com/maps/search/Troca+de+Fechaduras+Miolo+Segredo+Abertura+de+Carro+Casa+-+R.+Prof.+Zeferino+Ferraz+-+Itaim+Paulista,+S%C3%A3o+Paulo+-+SP,+08120-380"
    },
    {
      "mainName": "Troca de Segredos Aberturas de Portas Residenciais e Automotivas Chacára Klabin",
      "url": "https://www.google.com/maps/search/Troca+de+Segredos+Aberturas+de+Portas+Residenciais+e+Automotivas+Chac%C3%A1ra+Klabin+-+Rua+Vergueiro,+3766+-+Vila+Mariana,+S%C3%A3o+Paulo+-+SP,+04101-300"
    },
    {
      "mainName": "Chaveiro Gil Sales",
      "url": "https://www.google.com/maps/search/Chaveiro+Gil+Sales+-+R.+Boa+Vista,+523+B+-+Quiosque+01+-+Boa+Vista,+S%C3%A3o+Caetano+do+Sul+-+SP,+09572-300"
    },
    {
      "mainName": "Fort Chaaveiroo",
      "url": "https://www.google.com/maps/search/Fort+Chaaveiroo+-+R.+Eduardo+Prado,+2+-+SALA+22+-+S%C3%A3o+Jos%C3%A9,+S%C3%A3o+Caetano+do+Sul+-+SP,+09581-200"
    },
    {
      "mainName": "Fechaduras de Segurança",
      "url": "https://www.google.com/maps/search/Fechaduras+de+Seguran%C3%A7a+-+Av.+Guido+Aliberti,+3989+-+Mau%C3%A1,+S%C3%A3o+Caetano+do+Sul+-+SP,+09581-680"
    },
    {
      "mainName": "Alêba Chaveiro",
      "url": "https://www.google.com/maps/search/Al%C3%AAba+Chaveiro+-+Av.+Sen.+Roberto+S%C3%ADmonsen,+497+-+Cer%C3%A2mica,+S%C3%A3o+Caetano+do+Sul+-+SP,+09530-402"
    }
  ]
}