{
  "mainName": "Igreja Pentecostal Deus é Amor- IPDA Cosmos",
  "slug": "igreja-pentecostal-deus-e-amor-ipda-cosmos",
  "category": "Igreja Pentecostal",
  "locationInformation": {
    "latitude": "-22.9103111",
    "longitude": "-43.6034723"
  },
  "basicInformation": [
    {
      "label": "endereço",
      "tooltip": "Copiar endereço",
      "text": "R. Guarujá, 292 - Inhoaíba, Rio de Janeiro - RJ, 23060-660",
      "icon": "https://www.gstatic.com/images/icons/material/system_gm/1x/place_gm_blue_24dp.png"
    },
    {
      "label": "website",
      "tooltip": "Abrir website",
      "text": "ipda.com.br",
      "icon": "https://www.gstatic.com/images/icons/material/system_gm/1x/public_gm_blue_24dp.png"
    },
    {
      "label": "Code",
      "tooltip": "Copiar Plus Code",
      "text": "39QW+VJ Inhoaíba, Rio de Janeiro - RJ",
      "icon": "https://maps.gstatic.com/mapfiles/maps_lite/images/2x/ic_plus_code.png"
    },
    {
      "label": "send-to-device",
      "text": "Enviar para smartphone",
      "icon": "https://maps.gstatic.com/consumer/images/icons/1x/send_to_mobile_alt_gm_blue_24dp.png"
    },
    {
      "label": "merchant",
      "text": "Reivindicar esta empresa",
      "icon": "https://www.gstatic.com/images/icons/material/system_gm/1x/verified_user_gm_blue_24dp.png"
    }
  ],
  "ratingInformation": {
    "basicRatingInformation": {
      "averageGrade": 4.7,
      "totalOfEvaluations": 6
    },
    "ratingsByGrade": [
      {
        "grade": 5,
        "totalRatings": 5
      },
      {
        "grade": 4,
        "totalRatings": 0
      },
      {
        "grade": 3,
        "totalRatings": 1
      },
      {
        "grade": 2,
        "totalRatings": 0
      },
      {
        "grade": 1,
        "totalRatings": 0
      }
    ]
  },
  "ratingTags": null,
  "featuredPhotos": [
    "https://streetviewpixels-pa.googleapis.com/v1/thumbnail?panoid=5yglcSzsrw5D38BfxZVmZg&amp;cb_client=maps_sv.tactile.gps&amp;w=203&amp;h=100&amp;yaw=343.04117&amp;pitch=0&amp;thumbfov=100=w1024-h576-k-no",
    "https://lh5.googleusercontent.com/p/AF1QipMDt2kM-Do4kfwqaiqMEeqMpGISwmB0-1nxizs9=w1024-h576-k-no"
  ],
  "topComments": null,
  "peakHours": null,
  "relatedSearches": [
    "igreja deus é amor ao vivo agora",
    "doutrina deus é amor 2022",
    "ipda ao vivo agora youtube",
    "proibições da igreja deus é amor",
    "igreja deus é amor endereços",
    "número do whatsapp da igreja pentecostal deus é amor",
    "igreja deus é amor oficial",
    "igreja deus é amor mais próxima"
  ],
  "relateds": [
    {
      "mainName": "Igreja Pentecostal Deus é Amor",
      "url": "https://www.google.com/maps/search/Igreja+Pentecostal+Deus+%C3%A9+Amor+-+R.+Quatorze,+528b,+Morrinhos+-+GO,+75650-000"
    },
    {
      "mainName": "Igreja Pentecostal Deus é Amor",
      "url": "https://www.google.com/maps/search/Igreja+Pentecostal+Deus+%C3%A9+Amor+-+R.+Pernambuco,+344-450,+Morrinhos+-+GO,+75650-000"
    },
    {
      "mainName": "Igreja Pentecostal Deus É Amor",
      "url": "https://www.google.com/maps/search/Igreja+Pentecostal+Deus+%C3%89+Amor,+Piracanjuba+-+GO,+75640-000"
    },
    {
      "mainName": "Igreja Pentecostal Deus é Amor",
      "url": "https://www.google.com/maps/search/Igreja+Pentecostal+Deus+%C3%A9+Amor+-+R.+Rio+Branco,+1240+-+Goiatuba,+GO,+75600-000"
    }
  ],
  "editMode": false
}