{
  "mainName": "Lago da Juréia",
  "slug": "lago-da-jureia",
  "category": "água",
  "locationInformation": {
    "latitude": "-23.7630195",
    "longitude": "-45.7866395"
  },
  "basicInformation": [
    {
      "label": "endereço",
      "tooltip": "Copiar endereço",
      "text": "Maresias, São Sebastião - SP, 11600-000",
      "icon": "https://www.gstatic.com/images/icons/material/system_gm/1x/place_gm_blue_24dp.png"
    }
  ],
  "ratingInformation": {
    "basicRatingInformation": {
      "averageGrade": 4.6,
      "totalOfEvaluations": 34
    },
    "ratingsByGrade": [
      {
        "grade": 5,
        "totalRatings": 22
      },
      {
        "grade": 4,
        "totalRatings": 10
      },
      {
        "grade": 3,
        "totalRatings": 2
      },
      {
        "grade": 2,
        "totalRatings": 0
      },
      {
        "grade": 1,
        "totalRatings": 0
      }
    ]
  },
  "ratingTags": null,
  "featuredPhotos": [
    "https://lh5.googleusercontent.com/p/AF1QipM21n3kC6jrL8YyHl7mfu9jdSWuKlEgXqHumtw=w1024-h576-k-no",
    "https://lh5.googleusercontent.com/p/AF1QipNuMZyUShSbMJ4_FTZKMUJ8r3PIbSmeaG3Uxe8G=w1024-h576-k-no",
    "https://lh5.googleusercontent.com/p/AF1QipODd4Z6bSONNSjQ1HbP32jw3V12d26Hk-ZBilaY=w1024-h576-k-no",
    "https://lh5.googleusercontent.com/p/AF1QipO280Wf5N0BLTJQAkLDAynpPH0SZ90pBTDaYgA3=w1024-h576-k-no",
    "https://lh5.googleusercontent.com/p/AF1QipOUAMSxLatcE3mPWnu0JQYu_xEdKpT7zLSqGyp-=w1024-h576-k-no",
    "https://lh5.googleusercontent.com/p/AF1QipNTf__FCS4tLzB_IxbIpW0ZCv3zYQhE9leOGx4K=w1024-h576-k-no",
    "https://lh5.googleusercontent.com/p/AF1QipP36lkeCJWtyi1ZFSHCME8OiXDOcaJAeGZUsFEz=w1024-h576-k-no",
    "https://lh5.googleusercontent.com/p/AF1QipPusTHUC4LOD8CTuYtBpmqL40aYpJUZ3d1mDgs=w1024-h576-k-no",
    "https://lh5.googleusercontent.com/p/AF1QipOSFkfxEW2Ig-nLs417mVewczyYsp9T7nfG4ME=w1024-h576-k-no",
    "https://lh5.googleusercontent.com/p/AF1QipOnif2EL1rgeAmHSNsj09lBw5F8mD0QIBWaX944=w1024-h576-k-no",
    "https://lh5.googleusercontent.com/p/AF1QipPOeCd6g3OaTLPxXiVVJiuxQPEBDDtUIu2IpeBd=w1024-h576-k-no",
    "https://lh5.googleusercontent.com/p/AF1QipO9dSY-vnIuvzs0IoWzzN9569Y2O7psBb2sf9Mu=w1024-h576-k-no",
    "https://lh5.googleusercontent.com/p/AF1QipMOlaJD4JFjsbCeoK8vqEvlC3pcFgR95I_Qtegs=w1024-h576-k-no",
    "https://lh5.googleusercontent.com/p/AF1QipMpoyIdYnVPf2fh43SCTWFdGdUMmEHlvnB8isuG=w1024-h576-k-no",
    "https://lh5.googleusercontent.com/p/AF1QipM1Wq-1fBNrKQIif29qXKU3NRPT-v87ilox7AWw=w1024-h576-k-no",
    "https://lh5.googleusercontent.com/p/AF1QipPjLn9NAVFC5iX602KS8oNehrgHvcLwTkAuWAiG=w1024-h576-k-no",
    "https://lh5.googleusercontent.com/p/AF1QipOUTPTVgqcNzNst0gEEi8jJuwQqkFF-qpwF6V6h=w1024-h576-k-no",
    "https://lh5.googleusercontent.com/p/AF1QipNuoIC3o3mcAjkAvSJxueRpROL3EblbtN-ay4Pv=w1024-h576-k-no",
    "https://lh5.googleusercontent.com/p/AF1QipOg4IEi900vuF0UhDGUw7OAYFjrVB1vPD8S9OlO=w1024-h576-k-no"
  ],
  "topComments": null,
  "peakHours": null,
  "relatedSearches": [
    "juréia onde fica",
    "praia da juréia iguape fotos",
    "praia da juréia pousadas",
    "o que fazer em juréia",
    "praia juréia tempo",
    "jureia cachoeira",
    "praia do engenho",
    "barra do una",
    "juréia onde fica",
    "praia da juréia iguape fotos",
    "praia da juréia pousadas",
    "o que fazer em juréia",
    "praia juréia tempo",
    "jureia cachoeira",
    "praia do engenho",
    "barra do una"
  ],
  "relateds": []
}