{
  "mainName": "Six Flags México",
  "slug": "six-flags-mexico",
  "category": "Parque de diversão",
  "locationInformation": {
    "latitude": "19.2956057",
    "longitude": "-99.2105652"
  },
  "basicInformation": [
    {
      "label": "endereço",
      "tooltip": "Copiar endereço",
      "text": "Carr. Picacho-Ajusco Km 1.5, Jardines del Ajusco, Tlalpan, 14200 Ciudad de México, CDMX, México",
      "icon": "https://www.gstatic.com/images/icons/material/system_gm/1x/place_gm_blue_24dp.png"
    },
    {
      "label": "pedido",
      "tooltip": "Fazer um pedido",
      "text": "Fazer um pedido\nrappi.com.mx",
      "icon": "https://www.gstatic.com/images/icons/material/system_gm/1x/local_shipping_gm_blue_24dp.png"
    },
    {
      "label": "website",
      "tooltip": "Abrir website",
      "text": "sixflags.com.mx",
      "icon": "https://www.gstatic.com/images/icons/material/system_gm/1x/public_gm_blue_24dp.png"
    },
    {
      "label": "telefone",
      "tooltip": "Copiar número de telefone",
      "text": "+52 55 5339 3600",
      "icon": "https://www.gstatic.com/images/icons/material/system_gm/1x/phone_gm_blue_24dp.png"
    },
    {
      "label": "Code",
      "tooltip": "Copiar Plus Code",
      "text": "7QWQ+6Q Cidade do México, Distrito Federal, México",
      "icon": "https://maps.gstatic.com/mapfiles/maps_lite/images/2x/ic_plus_code.png"
    }
  ],
  "ratingInformation": {
    "basicRatingInformation": {
      "averageGrade": 4.6,
      "totalOfEvaluations": 138158
    },
    "ratingsByGrade": [
      {
        "grade": 5,
        "totalRatings": 99446
      },
      {
        "grade": 4,
        "totalRatings": 25813
      },
      {
        "grade": 3,
        "totalRatings": 7627
      },
      {
        "grade": 2,
        "totalRatings": 2155
      },
      {
        "grade": 1,
        "totalRatings": 3117
      }
    ]
  },
  "ratingTags": [
    {
      "tag": "acordo legal",
      "count": 41,
      "tooltip": "acordo legal, mencionado em 41 avaliações"
    },
    {
      "tag": "superman",
      "count": 500,
      "tooltip": "superman, mencionado em 500 avaliações"
    },
    {
      "tag": "desfile",
      "count": 312,
      "tooltip": "desfile, mencionado em 312 avaliações"
    },
    {
      "tag": "medusa",
      "count": 182,
      "tooltip": "medusa, mencionado em 182 avaliações"
    },
    {
      "tag": "destreza",
      "count": 147,
      "tooltip": "destreza, mencionado em 147 avaliações"
    },
    {
      "tag": "operador",
      "count": 67,
      "tooltip": "operador, mencionado em 67 avaliações"
    }
  ],
  "featuredPhotos": [
    "https://lh5.googleusercontent.com/p/AF1QipNSBjUdAkjBMb8m9AZWLVrMBzuAzVlMpiXwotSE=w1024-h576-k-no",
    "https://lh5.googleusercontent.com/p/AF1QipPvlyAUz6WhAwexeU3wIUgFRumscxTRHacbQmSO=w1024-h576-k-no",
    "https://lh5.googleusercontent.com/p/AF1QipMJaz7h1lhNoV-6OUeKi8pfmWXMUKeo-xbHr4Yf=w1024-h576-k-no",
    "https://lh5.googleusercontent.com/p/AF1QipM8luX7KzP9feD3yifI8iXlcIqM9WU61MBNtxM-=w1024-h576-k-no",
    "https://lh5.googleusercontent.com/p/AF1QipPE1fT0uqS_kUdsXZzDDmX36iRfbKYgCoVaH5qV=w1024-h576-k-no",
    "https://lh5.googleusercontent.com/p/AF1QipN2cng0dlomllrP3jpzNrd390SovEahcUOpRE4c=w1024-h576-k-no",
    "https://lh5.googleusercontent.com/p/AF1QipPAHacOq8omXxIO8hHP1NuUYsyAJMWz2zuQ07k9=w1024-h576-k-no",
    "https://lh5.googleusercontent.com/p/AF1QipNGGlvPq36JNrNWo8Vy-kIuzcO4ie9571hNF1iE=w1024-h576-k-no",
    "https://lh5.googleusercontent.com/p/AF1QipPe4SdEwh5YpkbDjQC_Q8wPuJrPhYMM6l0mywsi=w1024-h576-k-no",
    "https://lh5.googleusercontent.com/p/AF1QipPuYkJ8d2mJhhVFYax-sAMIgQVIB6GeYBXI2FBE=w1024-h576-k-no",
    "https://lh5.googleusercontent.com/p/AF1QipM_Nw65AB0L62rPCgn3-42r6uohu5F2pwHrsHfS=w1024-h576-k-no",
    "https://lh5.googleusercontent.com/p/AF1QipOqaInln-sjnfh1mJoiv0Po7zv65W8GUlYje7IA=w1024-h576-k-no",
    "https://lh5.googleusercontent.com/p/AF1QipO_vYkm4Yu7deSBoxI3giAKzw3r34TGAYOKC9bP=w1024-h576-k-no",
    "https://lh5.googleusercontent.com/p/AF1QipNS1Qc0T-KcYI5I6KBXXQh9AwN9hIW5Z9hYkvTU=w1024-h576-k-no",
    "https://lh5.googleusercontent.com/p/AF1QipPzNX7Lg_u-QKmLWDEXRm-zwgfbpYoICZaXS-Ue=w1024-h576-k-no",
    "https://lh5.googleusercontent.com/p/AF1QipOolZ1KmOoCvxorD8LYZkeBGhtXqQydL8uQqIX0=w1024-h576-k-no",
    "https://lh5.googleusercontent.com/p/AF1QipMrviddXFbqtOT7xKVFlftFQsoMS0AO5JEcv7sL=w1024-h576-k-no",
    "https://lh5.googleusercontent.com/p/AF1QipPDtVX_SSBX5JwNSZCj2-Ca7MlEXynGs2KZpdA-=w1024-h576-k-no",
    "https://lh5.googleusercontent.com/p/AF1QipMAjn54domap-bwjpuDeI8JRxNSuf5h9XUWWIbI=w1024-h576-k-no",
    "https://lh5.googleusercontent.com/p/AF1QipP5D2fDBYoSCR8w5smhDYCFVDYKQUnwKa_Eq4GD=w1024-h576-k-no",
    "https://lh5.googleusercontent.com/p/AF1QipNd1Ix7j8llzQdMZYlAgRLED8OVNZCVY8CYQRp_=w1024-h576-k-no",
    "https://lh5.googleusercontent.com/p/AF1QipNlvebu2OQsFxRoqOeX06yeG1W3Ykd7lm7mh9PX=w1024-h576-k-no"
  ],
  "topComments": [
    {
      "author": "Dine Moreira",
      "photoAuthor": "https://lh3.googleusercontent.com/a-/AFdZucoZHuRyV18Kn5AgAm23xHL8G9vj5j4ohdJa6TrJVro=w36-h36-p-c0x00000000-rp-mo-br100",
      "comment": "Lugar incrível e de ótimas atrações para diversão!",
      "gradeComment": 5
    },
    {
      "author": "Mariana Busch",
      "photoAuthor": "https://lh3.googleusercontent.com/a-/AFdZucqgk63e0mvppQn2kJYh-Zo3dCcC-RlrtbtBtPkwgw=w36-h36-p-c0x00000000-rp-mo-ba3-br100",
      "comment": "Amo os parques do six flags. Esse é mais “arrumadinho” que o da Califórnia. Mas tem bem menos opções de atrações. Gostei das montanhas russas, as minha preferidas foram a do batman e superman.",
      "gradeComment": 5
    },
    {
      "author": "André Araripe",
      "photoAuthor": "https://lh3.googleusercontent.com/a-/AFdZucp5kagDoJFgbmCuscBbkKQ2IkZl7K6c_P5K-g8xKsM=w36-h36-p-c0x00000000-rp-mo-ba6-br100",
      "comment": "O parque está localizado no bairro de Tlalpan. Gastamos 45 minutos para chegar devido a distância e ao trânsito da cidade do México. O parque tem um grande estacionamento bem na entrada.  No dia que fomos tinham muitos grupos de estudantes o que tornou a entrada um pouco caótica. O parque é imenso e dividido em Pueblos (Mexicano, Francês, Polinesio, Suiço,  Super Heróis, Vaqueiro, Villa Hollywood e Bugs Bonny Boon). A maioria das atrações são radicais, mas existem algumas mais tranquilas, como o rio corrente, logo no inicio do parque, mas molha bastante. Tem um cinema 4D com muitos efeitos. Além disso as montanhas russas são muito boas, com destaque para as da Mulher maravilha, Superman e do Batman. Quanto a comida senti falta de restaurantes fechados, não vi nenhum. Tem só lanchonetes onde reina a batata frita e o hamburguer, mas conseguimos comer tacos lá dentro. O ingresso custa 150,00 reais de acordo com a cotação de hoje, mas quando fui estava um pouco mais barato. Um passeio de dia inteiro que vale a pena.  Existem duas boas formas de chegar ao parque. Uma delas é pegar o metrô e saltar na estação Universidad e de lá pegar um uber até o parque ou um ônibus até o parque. A outra forma é se você comprar um ingresso do ônibus de turismo da cidade ele te leva de graça em outro dia a marcar. Foi assim que fomos e valeu muito a pena.",
      "gradeComment": 5
    },
    {
      "author": "iGausS_",
      "photoAuthor": "https://lh3.googleusercontent.com/a-/AFdZucoj4GK1AsIbigfxp6YsJ9GopalIH_j32cvMmULAKg=w36-h36-p-c0x00000000-rp-mo-ba3-br100",
      "comment": "Amooo❤",
      "gradeComment": 5
    },
    {
      "author": "Anninha Hartmann",
      "photoAuthor": "https://lh3.googleusercontent.com/a/AItbvmnvIhQXl34lMhv9iFKi_X7T-QFD82aXpcIQrMdL=w36-h36-p-c0x00000000-rp-mo-ba3-br100",
      "comment": "Amei!!! Meu filho de 4 anos, nunca brincou tanto!!! Super recomendo!!! Comida e bebida dentro do parque, com preço absurdo!!! Levem lanche!!!",
      "gradeComment": 5
    },
    {
      "author": "Gustavo Moraes",
      "photoAuthor": "https://lh3.googleusercontent.com/a-/AFdZuco8u-2Ptuilo1WKa6ALMR_lf9dVce-yE_9IKwBH8kM=w36-h36-p-c0x00000000-rp-mo-ba3-br100",
      "comment": "Lugar incrível. Porém precisa comprar VIP pass",
      "gradeComment": 5
    },
    {
      "author": "Thiago Simas",
      "photoAuthor": "https://lh3.googleusercontent.com/a-/AFdZucqcjUgDBXlh3u6nC5P2rYh3V_OPRLLX4EJcayPH33g=w36-h36-p-c0x00000000-rp-mo-ba5-br100",
      "comment": "Montanhas russas muito top, porém falta mais informacoes em inglês a maioria é somente em espanhol",
      "gradeComment": 5
    },
    {
      "author": "Amanda Nogueira",
      "photoAuthor": "https://lh3.googleusercontent.com/a-/AFdZucrF6jZNyLo8P3n0U_JYFIIXX3pgsuAbnvn9ZlWYZJg=w36-h36-p-c0x00000000-rp-mo-ba2-br100",
      "comment": "Paguei 599 pesos mas vale MT a pena",
      "gradeComment": 5
    },
    {
      "author": "Valter Jose",
      "photoAuthor": "https://lh3.googleusercontent.com/a-/AFdZucoxdzH1zuaClLPTBm44XNDNt_KsyDAxBtcMCr4Hnw=w36-h36-p-c0x00000000-rp-mo-br100",
      "comment": "Ótima, com várias opções de brinquedo s",
      "gradeComment": 5
    },
    {
      "author": "Juliano Guimarães Hofliger",
      "photoAuthor": "https://lh3.googleusercontent.com/a-/AFdZucoiHUB14N9_Yn69wi30fJ7J2P7BP8_kSCNri8TXdQ=w36-h36-p-c0x00000000-rp-mo-ba3-br100",
      "comment": "Os brinquedos são excelentes, muito divertidos. As opções de comida são muito boas também. O que poderia ser melhor, sem dúvida, é o tempo de espera. Perde-se muito tempo, que poderia ser usado indo em mais brinquedos. Alguns são cobrados à parte, também (além da entrada), mas não custam muito. Vale a pena passar uma tarde nesse lugar",
      "gradeComment": 4
    },
    {
      "author": "Nicola Occhipinti",
      "photoAuthor": "https://lh3.googleusercontent.com/a-/AFdZucrLE0hoCG9bKq799gvYN3ULcuTFw-RffFTcDarsUAA=w36-h36-p-c0x00000000-rp-mo-ba4-br100",
      "comment": "Muito legal, não vale a pena o Batman só",
      "gradeComment": 4
    },
    {
      "author": "Sergio Junior",
      "photoAuthor": "https://lh3.googleusercontent.com/a-/AFdZucpNuflsiflWGvvSBT2PGfPojgNEHxUJ1Gj1gWpYPHw=w36-h36-p-c0x00000000-rp-mo-ba4-br100",
      "comment": "O parque é legal e tem boas opções. Para grávidas, poucas opções. Deveria existir um pacote diferenciado. A fila de compra de ticket é uma bagunça, vão se abrindo caixas e os últimos das filas viram primeiros. No mais, vale uma visita",
      "gradeComment": 4
    },
    {
      "author": "alejandra berenice",
      "photoAuthor": "https://lh3.googleusercontent.com/a-/AFdZucq5FAZZ8nKBWLEdR8TXibYg88Sc1r4IhpMEFliTIQ=w36-h36-p-c0x00000000-rp-mo-br100",
      "comment": "Excelente dia",
      "gradeComment": 5
    },
    {
      "author": "Hugo Ferreira",
      "photoAuthor": "https://lh3.googleusercontent.com/a-/AFdZucoXBHBPsxwyMtOVWdOsas2MlfL8kfmJl8AIECtrB3k=w36-h36-p-c0x00000000-rp-mo-ba3-br100",
      "comment": "As atrações são muito mal sinalizadas e os preços das bebidas e comidas são muito altos.",
      "gradeComment": 3
    },
    {
      "author": "Caique Soares",
      "photoAuthor": "https://lh3.googleusercontent.com/a-/AFdZuco68HGsdn7B1TPA3_RgLfoVH6tr9-ir4OFQKI2S_7Q=w36-h36-p-c0x00000000-rp-mo-ba3-br100",
      "comment": "Vale muito a pena ir pelo menos 1 dia...",
      "gradeComment": 5
    },
    {
      "author": "Juliano Dias",
      "photoAuthor": "https://lh3.googleusercontent.com/a-/AFdZucrCzu3wvNzJEF6W_lGESkiRdX2WXJeOEiOTmE4Gz0A=w36-h36-p-c0x00000000-rp-mo-ba5-br100",
      "comment": "Super cheio porém super legal. Não vale a pena chegar cedo pois a fila é enorme. A dica é chegar por volta do meio dia pois a criançada já ta de saída e os primeiros brinquedos já não tem tanta fila. A noite o parque fica ainda melhor e sem filas.",
      "gradeComment": 5
    },
    {
      "author": "Hermann Vherner",
      "photoAuthor": "https://lh3.googleusercontent.com/a-/AFdZucq1QGofDbyXsvsVkMYXqPOfCvJV3Yt35qL3JZfPHw=w36-h36-p-c0x00000000-rp-mo-ba3-br100",
      "comment": "Divertido, muitos produtos para comprar, comida variada, porém, todos os brinquedos abertos até o momento são montanhas-russa. Falta variedade em relação a isso.",
      "gradeComment": 5
    },
    {
      "author": "Juan Jose Perez Castillo",
      "photoAuthor": "https://lh3.googleusercontent.com/a-/AFdZucqxmAcwduPvme4L6eiM7HdRK2uAjuz8BByNx8Y94A=w36-h36-p-c0x00000000-rp-mo-ba4-br100",
      "comment": "Execelente",
      "gradeComment": 5
    },
    {
      "author": "Rafaela Cruz Bórtoli",
      "photoAuthor": "https://lh3.googleusercontent.com/a-/AFdZucogs9YGxMy6U0H6QHJUyxt6oaHxU9CIYZ30ccyAPA=w36-h36-p-c0x00000000-rp-mo-ba4-br100",
      "comment": "Muito bom o parque, bem conservado. As montanhas russas são bem divertidas. Cuidado, os brinquedos que molham, molham mesmo! Acesso fácil de transporte público.",
      "gradeComment": 5
    },
    {
      "author": "Luciana Ferreira",
      "photoAuthor": "https://lh3.googleusercontent.com/a-/AFdZucrN0Mjs3I5rWQhedfI27WqhFp7ZL1jTnRVFFo15CQ=w36-h36-p-c0x00000000-rp-mo-ba4-br100",
      "comment": "Perfeito. Poderiam abrir um no Brasil",
      "gradeComment": 5
    }
  ],
  "peakHours": [
    {
      "Sunday": [
        {
          "hour": "10:00",
          "percent": 44
        },
        {
          "hour": "11:00",
          "percent": 61
        },
        {
          "hour": "12:00",
          "percent": 76
        },
        {
          "hour": "13:00",
          "percent": 89
        },
        {
          "hour": "14:00",
          "percent": 97
        },
        {
          "hour": "15:00",
          "percent": 100
        },
        {
          "hour": "16:00",
          "percent": 97
        },
        {
          "hour": "17:00",
          "percent": 88
        },
        {
          "hour": "18:00",
          "percent": 75
        },
        {
          "hour": "19:00",
          "percent": 58
        },
        {
          "hour": "20:00",
          "percent": 41
        }
      ]
    },
    {
      "Monday": []
    },
    {
      "Tuesday": []
    },
    {
      "Wednesday": []
    },
    {
      "Thursday": [
        {
          "hour": "11:00",
          "percent": 51
        },
        {
          "hour": "12:00",
          "percent": 67
        },
        {
          "hour": "13:00",
          "percent": 81
        },
        {
          "hour": "14:00",
          "percent": 90
        },
        {
          "hour": "15:00",
          "percent": 93
        },
        {
          "hour": "16:00",
          "percent": 88
        },
        {
          "hour": "17:00",
          "percent": 77
        },
        {
          "hour": "18:00",
          "percent": 62
        }
      ]
    },
    {
      "Friday": [
        {
          "hour": "10:00",
          "percent": 32
        },
        {
          "hour": "11:00",
          "percent": 43
        },
        {
          "hour": "12:00",
          "percent": 54
        },
        {
          "hour": "13:00",
          "percent": 63
        },
        {
          "hour": "14:00",
          "percent": 69
        },
        {
          "hour": "15:00",
          "percent": 72
        },
        {
          "hour": "16:00",
          "percent": 71
        },
        {
          "hour": "17:00",
          "percent": 65
        },
        {
          "hour": "18:00",
          "percent": 55
        },
        {
          "hour": "19:00",
          "percent": 42
        },
        {
          "hour": "20:00",
          "percent": 29
        }
      ]
    },
    {
      "Saturday": [
        {
          "hour": "10:00",
          "percent": 39
        },
        {
          "hour": "11:00",
          "percent": 56
        },
        {
          "hour": "12:00",
          "percent": 72
        },
        {
          "hour": "13:00",
          "percent": 83
        },
        {
          "hour": "14:00",
          "percent": 89
        },
        {
          "hour": "15:00",
          "percent": 91
        },
        {
          "hour": "16:00",
          "percent": 92
        },
        {
          "hour": "17:00",
          "percent": 90
        },
        {
          "hour": "18:00",
          "percent": 82
        },
        {
          "hour": "19:00",
          "percent": 68
        },
        {
          "hour": "20:00",
          "percent": 50
        }
      ]
    }
  ],
  "relatedSearches": [
    "six flags locais",
    "six flags texas",
    "six flags brasil",
    "six flags california tickets",
    "six flags magic mountain",
    "six flags florida",
    "six flags miami",
    "six flags superman"
  ],
  "relateds": [
    {
      "mainName": "Six Flags St. Louis",
      "url": null
    },
    {
      "mainName": "La Ronde",
      "url": null
    },
    {
      "mainName": "Six Flags White Water",
      "url": null
    },
    {
      "mainName": "Six Flags Hurricane Harbor",
      "url": null
    },
    {
      "mainName": "Six Flags Darien Lake",
      "url": null
    },
    {
      "mainName": "La Feria de Chapultepec Mágico",
      "url": null
    },
    {
      "mainName": "Medusa Steel Coaster",
      "url": null
    },
    {
      "mainName": "Six Flags Great Escape",
      "url": null
    },
    {
      "mainName": "Six Flags Great Adventure",
      "url": null
    },
    {
      "mainName": "Six Flags Great America",
      "url": null
    },
    {
      "mainName": "Six Flags Discovery Kingdom",
      "url": null
    },
    {
      "mainName": "Six Flags New England",
      "url": null
    },
    {
      "mainName": "Six Flags Magic Mountain",
      "url": null
    },
    {
      "mainName": "Six Flags America",
      "url": null
    },
    {
      "mainName": "Six Flags Over Georgia",
      "url": null
    },
    {
      "mainName": "Six Flags Fiesta Texas",
      "url": null
    },
    {
      "mainName": "Reino Aventura",
      "url": null
    },
    {
      "mainName": "Six Flags Over Texas",
      "url": null
    },
    {
      "mainName": "Six Flags Hurricane Harbor Oaxtepec",
      "url": null
    },
    {
      "mainName": "Aquário Inbursa",
      "url": null
    },
    {
      "mainName": "Frontier City",
      "url": null
    },
    {
      "mainName": "Chapultepec",
      "url": null
    },
    {
      "mainName": "Zoológico Los Coyotes",
      "url": null
    },
    {
      "mainName": "Zoológico de Chapultepec",
      "url": null
    }
  ]
}